{
  "date": "2026-04-24",
  "updated": "2026-04-24T21:06:06.523932+09:00",
  "venues": [
    {
      "name": "浦和",
      "code": 18,
      "races": [
        {
          "raceNo": 1,
          "entries": [
            {
              "hn": 1,
              "pop": 2,
              "odds": 9.7,
              "pos": 3
            },
            {
              "hn": 2,
              "pop": 9,
              "odds": 56.4,
              "pos": null
            },
            {
              "hn": 3,
              "pop": 6,
              "odds": 35.7,
              "pos": null
            },
            {
              "hn": 4,
              "pop": 5,
              "odds": 25.4,
              "pos": null
            },
            {
              "hn": 5,
              "pop": 1,
              "odds": 1.1,
              "pos": 1
            },
            {
              "hn": 6,
              "pop": 10,
              "odds": 150.2,
              "pos": null
            },
            {
              "hn": 7,
              "pop": 3,
              "odds": 9.8,
              "pos": 2
            },
            {
              "hn": 8,
              "pop": 4,
              "odds": 14.4,
              "pos": null
            },
            {
              "hn": 9,
              "pop": 7,
              "odds": 44.6,
              "pos": null
            },
            {
              "hn": 10,
              "pop": 11,
              "odds": 187.8,
              "pos": null
            },
            {
              "hn": 11,
              "pop": 8,
              "odds": 44.9,
              "pos": null
            }
          ]
        },
        {
          "raceNo": 2,
          "entries": [
            {
              "hn": 1,
              "pop": 3,
              "odds": 5.4,
              "pos": 3
            },
            {
              "hn": 2,
              "pop": 5,
              "odds": 8.5,
              "pos": null
            },
            {
              "hn": 3,
              "pop": 10,
              "odds": 143.8,
              "pos": null
            },
            {
              "hn": 4,
              "pop": 8,
              "odds": 38.7,
              "pos": null
            },
            {
              "hn": 5,
              "pop": 7,
              "odds": 28.4,
              "pos": null
            },
            {
              "hn": 6,
              "pop": 12,
              "odds": 178.4,
              "pos": 2
            },
            {
              "hn": 7,
              "pop": 9,
              "odds": 68.0,
              "pos": null
            },
            {
              "hn": 8,
              "pop": 11,
              "odds": 173.8,
              "pos": null
            },
            {
              "hn": 9,
              "pop": 2,
              "odds": 3.2,
              "pos": 1
            },
            {
              "hn": 10,
              "pop": 1,
              "odds": 2.8,
              "pos": null
            },
            {
              "hn": 11,
              "pop": 4,
              "odds": 7.1,
              "pos": null
            },
            {
              "hn": 12,
              "pop": 6,
              "odds": 17.9,
              "pos": null
            }
          ]
        },
        {
          "raceNo": 3,
          "entries": [
            {
              "hn": 1,
              "pop": 8,
              "odds": 43.9,
              "pos": null
            },
            {
              "hn": 2,
              "pop": 6,
              "odds": 35.3,
              "pos": null
            },
            {
              "hn": 3,
              "pop": 7,
              "odds": 40.8,
              "pos": null
            },
            {
              "hn": 4,
              "pop": 2,
              "odds": 7.9,
              "pos": 3
            },
            {
              "hn": 5,
              "pop": 1,
              "odds": 1.2,
              "pos": 1
            },
            {
              "hn": 6,
              "pop": 5,
              "odds": 22.0,
              "pos": null
            },
            {
              "hn": 7,
              "pop": 10,
              "odds": 133.0,
              "pos": null
            },
            {
              "hn": 8,
              "pop": 9,
              "odds": 94.3,
              "pos": null
            },
            {
              "hn": 9,
              "pop": 4,
              "odds": 15.0,
              "pos": null
            },
            {
              "hn": 10,
              "pop": 3,
              "odds": 9.1,
              "pos": 2
            }
          ]
        },
        {
          "raceNo": 4,
          "entries": [
            {
              "hn": 1,
              "pop": 7,
              "odds": 47.5,
              "pos": null
            },
            {
              "hn": 2,
              "pop": 10,
              "odds": 148.4,
              "pos": null
            },
            {
              "hn": 3,
              "pop": 6,
              "odds": 20.7,
              "pos": null
            },
            {
              "hn": 4,
              "pop": 1,
              "odds": 1.8,
              "pos": 1
            },
            {
              "hn": 5,
              "pop": 9,
              "odds": 140.1,
              "pos": null
            },
            {
              "hn": 6,
              "pop": 2,
              "odds": 3.2,
              "pos": null
            },
            {
              "hn": 7,
              "pop": 5,
              "odds": 16.4,
              "pos": null
            },
            {
              "hn": 8,
              "pop": 4,
              "odds": 8.8,
              "pos": 3
            },
            {
              "hn": 9,
              "pop": 3,
              "odds": 7.3,
              "pos": 2
            },
            {
              "hn": 10,
              "pop": 8,
              "odds": 74.0,
              "pos": null
            }
          ]
        },
        {
          "raceNo": 5,
          "entries": [
            {
              "hn": 1,
              "pop": 8,
              "odds": 263.6,
              "pos": null
            },
            {
              "hn": 2,
              "pop": 7,
              "odds": 100.9,
              "pos": null
            },
            {
              "hn": 3,
              "pop": 6,
              "odds": 87.9,
              "pos": null
            },
            {
              "hn": 4,
              "pop": 2,
              "odds": 3.6,
              "pos": 3
            },
            {
              "hn": 5,
              "pop": 5,
              "odds": 21.0,
              "pos": null
            },
            {
              "hn": 6,
              "pop": 3,
              "odds": 10.3,
              "pos": null
            },
            {
              "hn": 7,
              "pop": 9,
              "odds": 306.9,
              "pos": null
            },
            {
              "hn": 8,
              "pop": 1,
              "odds": 1.3,
              "pos": 2
            },
            {
              "hn": 9,
              "pop": 4,
              "odds": 12.7,
              "pos": 1
            }
          ]
        },
        {
          "raceNo": 6,
          "entries": [
            {
              "hn": 1,
              "pop": 5,
              "odds": 14.6,
              "pos": null
            },
            {
              "hn": 2,
              "pop": 6,
              "odds": 19.4,
              "pos": null
            },
            {
              "hn": 3,
              "pop": 2,
              "odds": 4.9,
              "pos": null
            },
            {
              "hn": 4,
              "pop": 8,
              "odds": 27.2,
              "pos": null
            },
            {
              "hn": 5,
              "pop": 3,
              "odds": 6.0,
              "pos": 2
            },
            {
              "hn": 6,
              "pop": 10,
              "odds": 96.0,
              "pos": null
            },
            {
              "hn": 7,
              "pop": 11,
              "odds": 149.2,
              "pos": null
            },
            {
              "hn": 8,
              "pop": 4,
              "odds": 7.6,
              "pos": 1
            },
            {
              "hn": 9,
              "pop": 6,
              "odds": 19.4,
              "pos": null
            },
            {
              "hn": 10,
              "pop": 1,
              "odds": 1.9,
              "pos": null
            },
            {
              "hn": 11,
              "pop": 9,
              "odds": 42.5,
              "pos": null
            },
            {
              "hn": 12,
              "pop": 12,
              "odds": 346.7,
              "pos": 3
            }
          ]
        },
        {
          "raceNo": 7,
          "entries": [
            {
              "hn": 1,
              "pop": 8,
              "odds": 43.8,
              "pos": null
            },
            {
              "hn": 2,
              "pop": 3,
              "odds": 5.4,
              "pos": null
            },
            {
              "hn": 3,
              "pop": 11,
              "odds": 192.9,
              "pos": null
            },
            {
              "hn": 4,
              "pop": 4,
              "odds": 5.7,
              "pos": null
            },
            {
              "hn": 5,
              "pop": 10,
              "odds": 131.2,
              "pos": null
            },
            {
              "hn": 6,
              "pop": 1,
              "odds": 2.9,
              "pos": 2
            },
            {
              "hn": 7,
              "pop": 2,
              "odds": 3.2,
              "pos": 1
            },
            {
              "hn": 8,
              "pop": 5,
              "odds": 9.9,
              "pos": 3
            },
            {
              "hn": 9,
              "pop": 9,
              "odds": 102.4,
              "pos": null
            },
            {
              "hn": 10,
              "pop": 7,
              "odds": 41.6,
              "pos": null
            },
            {
              "hn": 11,
              "pop": 6,
              "odds": 11.9,
              "pos": null
            }
          ]
        },
        {
          "raceNo": 8,
          "entries": [
            {
              "hn": 1,
              "pop": 3,
              "odds": 12.6,
              "pos": null
            },
            {
              "hn": 2,
              "pop": 4,
              "odds": 15.7,
              "pos": null
            },
            {
              "hn": 3,
              "pop": 2,
              "odds": 7.0,
              "pos": null
            },
            {
              "hn": 4,
              "pop": 7,
              "odds": 205.8,
              "pos": null
            },
            {
              "hn": 5,
              "pop": 5,
              "odds": 19.1,
              "pos": 1
            },
            {
              "hn": 6,
              "pop": 1,
              "odds": 1.1,
              "pos": 2
            },
            {
              "hn": 7,
              "pop": 6,
              "odds": 53.2,
              "pos": 3
            }
          ]
        },
        {
          "raceNo": 9,
          "entries": [
            {
              "hn": 1,
              "pop": 3,
              "odds": 6.6,
              "pos": null
            },
            {
              "hn": 2,
              "pop": 2,
              "odds": 6.3,
              "pos": 1
            },
            {
              "hn": 3,
              "pop": 4,
              "odds": 8.5,
              "pos": null
            },
            {
              "hn": 4,
              "pop": 6,
              "odds": 26.3,
              "pos": null
            },
            {
              "hn": 5,
              "pop": 1,
              "odds": 1.5,
              "pos": 3
            },
            {
              "hn": 6,
              "pop": 5,
              "odds": 10.6,
              "pos": 2
            },
            {
              "hn": 7,
              "pop": 8,
              "odds": 40.1,
              "pos": null
            },
            {
              "hn": 8,
              "pop": 7,
              "odds": 39.9,
              "pos": null
            }
          ]
        },
        {
          "raceNo": 10,
          "entries": [
            {
              "hn": 1,
              "pop": 12,
              "odds": 258.2,
              "pos": null
            },
            {
              "hn": 2,
              "pop": 2,
              "odds": 4.8,
              "pos": null
            },
            {
              "hn": 3,
              "pop": 6,
              "odds": 21.6,
              "pos": null
            },
            {
              "hn": 4,
              "pop": 9,
              "odds": 69.9,
              "pos": null
            },
            {
              "hn": 5,
              "pop": 7,
              "odds": 35.6,
              "pos": null
            },
            {
              "hn": 6,
              "pop": 1,
              "odds": 1.5,
              "pos": 1
            },
            {
              "hn": 7,
              "pop": 11,
              "odds": 242.1,
              "pos": null
            },
            {
              "hn": 8,
              "pop": 10,
              "odds": 220.7,
              "pos": null
            },
            {
              "hn": 9,
              "pop": 8,
              "odds": 38.0,
              "pos": null
            },
            {
              "hn": 10,
              "pop": 4,
              "odds": 15.4,
              "pos": 2
            },
            {
              "hn": 11,
              "pop": 5,
              "odds": 21.1,
              "pos": null
            },
            {
              "hn": 12,
              "pop": 3,
              "odds": 5.7,
              "pos": 3
            }
          ]
        },
        {
          "raceNo": 11,
          "entries": [
            {
              "hn": 1,
              "pop": 8,
              "odds": 54.2,
              "pos": null
            },
            {
              "hn": 2,
              "pop": 7,
              "odds": 18.2,
              "pos": null
            },
            {
              "hn": 3,
              "pop": 6,
              "odds": 13.3,
              "pos": null
            },
            {
              "hn": 4,
              "pop": 2,
              "odds": 3.7,
              "pos": 3
            },
            {
              "hn": 5,
              "pop": 4,
              "odds": 12.1,
              "pos": 2
            },
            {
              "hn": 6,
              "pop": 9,
              "odds": 83.0,
              "pos": null
            },
            {
              "hn": 7,
              "pop": 3,
              "odds": 4.3,
              "pos": null
            },
            {
              "hn": 8,
              "pop": 1,
              "odds": 2.4,
              "pos": 1
            },
            {
              "hn": 9,
              "pop": 5,
              "odds": 12.7,
              "pos": null
            },
            {
              "hn": 10,
              "pop": 10,
              "odds": 95.3,
              "pos": null
            },
            {
              "hn": 11,
              "pop": 11,
              "odds": 257.3,
              "pos": null
            }
          ]
        },
        {
          "raceNo": 12,
          "entries": [
            {
              "hn": 1,
              "pop": 6,
              "odds": 14.7,
              "pos": null
            },
            {
              "hn": 2,
              "pop": 4,
              "odds": 9.0,
              "pos": null
            },
            {
              "hn": 3,
              "pop": 1,
              "odds": 2.5,
              "pos": 1
            },
            {
              "hn": 4,
              "pop": 2,
              "odds": 4.1,
              "pos": null
            },
            {
              "hn": 5,
              "pop": 12,
              "odds": 97.3,
              "pos": null
            },
            {
              "hn": 6,
              "pop": 10,
              "odds": 51.6,
              "pos": null
            },
            {
              "hn": 7,
              "pop": 11,
              "odds": 72.6,
              "pos": null
            },
            {
              "hn": 8,
              "pop": 5,
              "odds": 14.3,
              "pos": null
            },
            {
              "hn": 9,
              "pop": 3,
              "odds": 5.2,
              "pos": 3
            },
            {
              "hn": 10,
              "pop": 7,
              "odds": 15.8,
              "pos": 2
            },
            {
              "hn": 11,
              "pop": 9,
              "odds": 41.0,
              "pos": null
            },
            {
              "hn": 12,
              "pop": 8,
              "odds": 20.6,
              "pos": null
            }
          ]
        }
      ]
    },
    {
      "name": "金沢",
      "code": 22,
      "races": [
        {
          "raceNo": 1,
          "entries": [
            {
              "hn": 1,
              "pop": 8,
              "odds": 48.1,
              "pos": null
            },
            {
              "hn": 2,
              "pop": 1,
              "odds": 1.6,
              "pos": 2
            },
            {
              "hn": 3,
              "pop": 2,
              "odds": 6.0,
              "pos": null
            },
            {
              "hn": 4,
              "pop": 5,
              "odds": 12.2,
              "pos": 1
            },
            {
              "hn": 5,
              "pop": 3,
              "odds": 8.9,
              "pos": null
            },
            {
              "hn": 6,
              "pop": 6,
              "odds": 15.0,
              "pos": null
            },
            {
              "hn": 7,
              "pop": 4,
              "odds": 9.1,
              "pos": null
            },
            {
              "hn": 8,
              "pop": 9,
              "odds": 65.4,
              "pos": null
            },
            {
              "hn": 9,
              "pop": 7,
              "odds": 16.6,
              "pos": 3
            }
          ]
        },
        {
          "raceNo": 2,
          "entries": [
            {
              "hn": 1,
              "pop": 3,
              "odds": 6.5,
              "pos": 2
            },
            {
              "hn": 2,
              "pop": 1,
              "odds": 1.1,
              "pos": 1
            },
            {
              "hn": 3,
              "pop": 4,
              "odds": 38.5,
              "pos": null
            },
            {
              "hn": 4,
              "pop": 5,
              "odds": 38.6,
              "pos": null
            },
            {
              "hn": 5,
              "pop": 6,
              "odds": 72.9,
              "pos": null
            },
            {
              "hn": 6,
              "pop": 2,
              "odds": 6.0,
              "pos": 3
            },
            {
              "hn": 7,
              "pop": 8,
              "odds": 243.2,
              "pos": null
            },
            {
              "hn": 8,
              "pop": 7,
              "odds": 92.0,
              "pos": null
            },
            {
              "hn": 9,
              "pop": 9,
              "odds": 279.9,
              "pos": null
            }
          ]
        },
        {
          "raceNo": 3,
          "entries": [
            {
              "hn": 1,
              "pop": 9,
              "odds": 196.1,
              "pos": null
            },
            {
              "hn": 2,
              "pop": 8,
              "odds": 84.0,
              "pos": null
            },
            {
              "hn": 3,
              "pop": 7,
              "odds": 42.8,
              "pos": null
            },
            {
              "hn": 4,
              "pop": 5,
              "odds": 15.6,
              "pos": 3
            },
            {
              "hn": 5,
              "pop": 4,
              "odds": 10.9,
              "pos": 2
            },
            {
              "hn": 6,
              "pop": 2,
              "odds": 3.7,
              "pos": null
            },
            {
              "hn": 7,
              "pop": 3,
              "odds": 4.8,
              "pos": null
            },
            {
              "hn": 8,
              "pop": 6,
              "odds": 21.6,
              "pos": null
            },
            {
              "hn": 9,
              "pop": 1,
              "odds": 1.8,
              "pos": 1
            }
          ]
        },
        {
          "raceNo": 4,
          "entries": [
            {
              "hn": 1,
              "pop": 5,
              "odds": 61.9,
              "pos": null
            },
            {
              "hn": 2,
              "pop": 8,
              "odds": 153.6,
              "pos": null
            },
            {
              "hn": 3,
              "pop": 7,
              "odds": 97.8,
              "pos": null
            },
            {
              "hn": 4,
              "pop": 1,
              "odds": 1.0,
              "pos": 1
            },
            {
              "hn": 5,
              "pop": 4,
              "odds": 40.3,
              "pos": null
            },
            {
              "hn": 6,
              "pop": 2,
              "odds": 12.9,
              "pos": 2
            },
            {
              "hn": 7,
              "pop": 3,
              "odds": 22.9,
              "pos": 3
            },
            {
              "hn": 8,
              "pop": 6,
              "odds": 77.8,
              "pos": null
            }
          ]
        },
        {
          "raceNo": 5,
          "entries": [
            {
              "hn": 1,
              "pop": 5,
              "odds": 35.9,
              "pos": null
            },
            {
              "hn": 2,
              "pop": 2,
              "odds": 2.0,
              "pos": null
            },
            {
              "hn": 3,
              "pop": 4,
              "odds": 13.0,
              "pos": 3
            },
            {
              "hn": 4,
              "pop": 3,
              "odds": 11.6,
              "pos": 1
            },
            {
              "hn": 5,
              "pop": 7,
              "odds": 114.0,
              "pos": null
            },
            {
              "hn": 6,
              "pop": 8,
              "odds": 119.9,
              "pos": null
            },
            {
              "hn": 7,
              "pop": 6,
              "odds": 58.1,
              "pos": null
            },
            {
              "hn": 8,
              "pop": 1,
              "odds": 1.8,
              "pos": 2
            }
          ]
        },
        {
          "raceNo": 6,
          "entries": [
            {
              "hn": 1,
              "pop": 6,
              "odds": 28.4,
              "pos": null
            },
            {
              "hn": 2,
              "pop": 7,
              "odds": 65.0,
              "pos": null
            },
            {
              "hn": 3,
              "pop": 8,
              "odds": 233.5,
              "pos": null
            },
            {
              "hn": 4,
              "pop": 4,
              "odds": 11.1,
              "pos": null
            },
            {
              "hn": 5,
              "pop": 3,
              "odds": 9.0,
              "pos": null
            },
            {
              "hn": 6,
              "pop": 2,
              "odds": 4.0,
              "pos": 1
            },
            {
              "hn": 7,
              "pop": 1,
              "odds": 1.4,
              "pos": 2
            },
            {
              "hn": 8,
              "pop": 5,
              "odds": 22.4,
              "pos": 3
            },
            {
              "hn": 9,
              "pop": 9,
              "odds": 255.2,
              "pos": null
            }
          ]
        },
        {
          "raceNo": 7,
          "entries": [
            {
              "hn": 1,
              "pop": 2,
              "odds": 8.4,
              "pos": null
            },
            {
              "hn": 2,
              "pop": 7,
              "odds": 71.2,
              "pos": null
            },
            {
              "hn": 3,
              "pop": 4,
              "odds": 10.3,
              "pos": 3
            },
            {
              "hn": 4,
              "pop": 5,
              "odds": 35.5,
              "pos": null
            },
            {
              "hn": 5,
              "pop": 8,
              "odds": 207.9,
              "pos": null
            },
            {
              "hn": 6,
              "pop": 3,
              "odds": 9.4,
              "pos": 2
            },
            {
              "hn": 7,
              "pop": 6,
              "odds": 54.6,
              "pos": null
            },
            {
              "hn": 8,
              "pop": 1,
              "odds": 1.1,
              "pos": 1
            }
          ]
        },
        {
          "raceNo": 8,
          "entries": [
            {
              "hn": 1,
              "pop": 4,
              "odds": 11.6,
              "pos": 2
            },
            {
              "hn": 2,
              "pop": 5,
              "odds": 28.0,
              "pos": 1
            },
            {
              "hn": 3,
              "pop": 9,
              "odds": 48.2,
              "pos": null
            },
            {
              "hn": 4,
              "pop": 8,
              "odds": 44.6,
              "pos": null
            },
            {
              "hn": 5,
              "pop": 6,
              "odds": 30.1,
              "pos": null
            },
            {
              "hn": 6,
              "pop": 3,
              "odds": 9.4,
              "pos": null
            },
            {
              "hn": 7,
              "pop": 7,
              "odds": 34.3,
              "pos": null
            },
            {
              "hn": 8,
              "pop": 1,
              "odds": 1.6,
              "pos": 3
            },
            {
              "hn": 9,
              "pop": 2,
              "odds": 3.1,
              "pos": null
            },
            {
              "hn": 10,
              "pop": 10,
              "odds": 312.9,
              "pos": null
            }
          ]
        },
        {
          "raceNo": 9,
          "entries": [
            {
              "hn": 1,
              "pop": 10,
              "odds": 225.8,
              "pos": null
            },
            {
              "hn": 2,
              "pop": 5,
              "odds": 8.8,
              "pos": 1
            },
            {
              "hn": 3,
              "pop": 2,
              "odds": 3.8,
              "pos": null
            },
            {
              "hn": 4,
              "pop": 3,
              "odds": 4.1,
              "pos": null
            },
            {
              "hn": 5,
              "pop": 8,
              "odds": 70.1,
              "pos": null
            },
            {
              "hn": 6,
              "pop": 6,
              "odds": 19.7,
              "pos": null
            },
            {
              "hn": 7,
              "pop": 7,
              "odds": 39.3,
              "pos": 3
            },
            {
              "hn": 8,
              "pop": 9,
              "odds": 76.1,
              "pos": null
            },
            {
              "hn": 9,
              "pop": 4,
              "odds": 4.4,
              "pos": 2
            },
            {
              "hn": 10,
              "pop": 1,
              "odds": 3.3,
              "pos": null
            }
          ]
        },
        {
          "raceNo": 10,
          "entries": [
            {
              "hn": 1,
              "pop": 1,
              "odds": 1.9,
              "pos": null
            },
            {
              "hn": 2,
              "pop": 3,
              "odds": 4.9,
              "pos": 1
            },
            {
              "hn": 3,
              "pop": 8,
              "odds": 81.0,
              "pos": null
            },
            {
              "hn": 4,
              "pop": 6,
              "odds": 34.2,
              "pos": null
            },
            {
              "hn": 5,
              "pop": 5,
              "odds": 16.3,
              "pos": 3
            },
            {
              "hn": 6,
              "pop": 4,
              "odds": 12.5,
              "pos": null
            },
            {
              "hn": 7,
              "pop": 9,
              "odds": 85.9,
              "pos": null
            },
            {
              "hn": 8,
              "pop": 10,
              "odds": 224.1,
              "pos": null
            },
            {
              "hn": 9,
              "pop": 7,
              "odds": 55.7,
              "pos": null
            },
            {
              "hn": 10,
              "pop": 2,
              "odds": 3.1,
              "pos": 2
            }
          ]
        },
        {
          "raceNo": 11,
          "entries": [
            {
              "hn": 1,
              "pop": 5,
              "odds": 19.4,
              "pos": null
            },
            {
              "hn": 2,
              "pop": 8,
              "odds": 45.5,
              "pos": null
            },
            {
              "hn": 3,
              "pop": 10,
              "odds": 82.7,
              "pos": null
            },
            {
              "hn": 4,
              "pop": 6,
              "odds": 30.7,
              "pos": null
            },
            {
              "hn": 5,
              "pop": 4,
              "odds": 17.9,
              "pos": null
            },
            {
              "hn": 6,
              "pop": 1,
              "odds": 1.1,
              "pos": 1
            },
            {
              "hn": 7,
              "pop": 9,
              "odds": 55.9,
              "pos": null
            },
            {
              "hn": 8,
              "pop": 12,
              "odds": 354.9,
              "pos": null
            },
            {
              "hn": 9,
              "pop": 2,
              "odds": 14.4,
              "pos": null
            },
            {
              "hn": 10,
              "pop": 7,
              "odds": 31.8,
              "pos": null
            },
            {
              "hn": 11,
              "pop": 3,
              "odds": 14.6,
              "pos": 3
            },
            {
              "hn": 12,
              "pop": 11,
              "odds": 90.9,
              "pos": 2
            }
          ]
        },
        {
          "raceNo": 12,
          "entries": [
            {
              "hn": 1,
              "pop": 1,
              "odds": 1.0,
              "pos": 1
            },
            {
              "hn": 2,
              "pop": 3,
              "odds": 19.3,
              "pos": null
            },
            {
              "hn": 3,
              "pop": 7,
              "odds": 109.8,
              "pos": null
            },
            {
              "hn": 4,
              "pop": null,
              "odds": null,
              "pos": null
            },
            {
              "hn": 5,
              "pop": 2,
              "odds": 14.3,
              "pos": 3
            },
            {
              "hn": 6,
              "pop": 8,
              "odds": 136.7,
              "pos": null
            },
            {
              "hn": 7,
              "pop": 5,
              "odds": 46.1,
              "pos": 2
            },
            {
              "hn": 8,
              "pop": 4,
              "odds": 23.2,
              "pos": null
            },
            {
              "hn": 9,
              "pop": 6,
              "odds": 66.7,
              "pos": null
            }
          ]
        }
      ]
    },
    {
      "name": "名古屋",
      "code": 24,
      "races": [
        {
          "raceNo": 1,
          "entries": [
            {
              "hn": 1,
              "pop": 11,
              "odds": 198.0,
              "pos": null
            },
            {
              "hn": 2,
              "pop": 5,
              "odds": 25.0,
              "pos": null
            },
            {
              "hn": 3,
              "pop": 6,
              "odds": 38.6,
              "pos": null
            },
            {
              "hn": 4,
              "pop": 1,
              "odds": 1.4,
              "pos": null
            },
            {
              "hn": 5,
              "pop": 12,
              "odds": 211.1,
              "pos": 2
            },
            {
              "hn": 6,
              "pop": 7,
              "odds": 45.7,
              "pos": null
            },
            {
              "hn": 7,
              "pop": 4,
              "odds": 16.7,
              "pos": 1
            },
            {
              "hn": 8,
              "pop": 9,
              "odds": 101.9,
              "pos": 3
            },
            {
              "hn": 9,
              "pop": 3,
              "odds": 7.0,
              "pos": null
            },
            {
              "hn": 10,
              "pop": 10,
              "odds": 165.2,
              "pos": null
            },
            {
              "hn": 11,
              "pop": 8,
              "odds": 47.7,
              "pos": null
            },
            {
              "hn": 12,
              "pop": 2,
              "odds": 4.6,
              "pos": null
            }
          ]
        },
        {
          "raceNo": 2,
          "entries": [
            {
              "hn": 1,
              "pop": 6,
              "odds": 48.8,
              "pos": null
            },
            {
              "hn": 2,
              "pop": 4,
              "odds": 25.4,
              "pos": null
            },
            {
              "hn": 3,
              "pop": 9,
              "odds": 161.9,
              "pos": null
            },
            {
              "hn": 4,
              "pop": 7,
              "odds": 73.1,
              "pos": null
            },
            {
              "hn": 5,
              "pop": 12,
              "odds": 239.1,
              "pos": null
            },
            {
              "hn": 6,
              "pop": 8,
              "odds": 81.4,
              "pos": null
            },
            {
              "hn": 7,
              "pop": 3,
              "odds": 7.7,
              "pos": null
            },
            {
              "hn": 8,
              "pop": 1,
              "odds": 2.0,
              "pos": 1
            },
            {
              "hn": 9,
              "pop": 1,
              "odds": 2.0,
              "pos": 2
            },
            {
              "hn": 10,
              "pop": 10,
              "odds": 174.1,
              "pos": 3
            },
            {
              "hn": 11,
              "pop": 11,
              "odds": 216.7,
              "pos": null
            },
            {
              "hn": 12,
              "pop": 5,
              "odds": 27.6,
              "pos": null
            }
          ]
        },
        {
          "raceNo": 3,
          "entries": [
            {
              "hn": 1,
              "pop": 10,
              "odds": 105.5,
              "pos": null
            },
            {
              "hn": 2,
              "pop": 1,
              "odds": 2.5,
              "pos": 3
            },
            {
              "hn": 3,
              "pop": 12,
              "odds": 260.7,
              "pos": null
            },
            {
              "hn": 4,
              "pop": 3,
              "odds": 5.4,
              "pos": null
            },
            {
              "hn": 5,
              "pop": 7,
              "odds": 42.5,
              "pos": 2
            },
            {
              "hn": 6,
              "pop": 5,
              "odds": 12.5,
              "pos": null
            },
            {
              "hn": 7,
              "pop": 8,
              "odds": 80.1,
              "pos": null
            },
            {
              "hn": 8,
              "pop": 9,
              "odds": 97.4,
              "pos": null
            },
            {
              "hn": 9,
              "pop": 6,
              "odds": 14.4,
              "pos": null
            },
            {
              "hn": 10,
              "pop": 11,
              "odds": 161.5,
              "pos": null
            },
            {
              "hn": 11,
              "pop": 4,
              "odds": 6.8,
              "pos": null
            },
            {
              "hn": 12,
              "pop": 2,
              "odds": 3.1,
              "pos": 1
            }
          ]
        },
        {
          "raceNo": 4,
          "entries": [
            {
              "hn": 1,
              "pop": 8,
              "odds": 75.2,
              "pos": null
            },
            {
              "hn": 2,
              "pop": 3,
              "odds": 11.7,
              "pos": null
            },
            {
              "hn": 3,
              "pop": 11,
              "odds": 454.1,
              "pos": null
            },
            {
              "hn": 4,
              "pop": 9,
              "odds": 259.5,
              "pos": null
            },
            {
              "hn": 5,
              "pop": 7,
              "odds": 59.3,
              "pos": null
            },
            {
              "hn": 6,
              "pop": 12,
              "odds": 483.4,
              "pos": null
            },
            {
              "hn": 7,
              "pop": 5,
              "odds": 17.7,
              "pos": 2
            },
            {
              "hn": 8,
              "pop": 1,
              "odds": 1.8,
              "pos": null
            },
            {
              "hn": 9,
              "pop": 10,
              "odds": 365.5,
              "pos": null
            },
            {
              "hn": 10,
              "pop": 4,
              "odds": 12.2,
              "pos": null
            },
            {
              "hn": 11,
              "pop": 6,
              "odds": 49.9,
              "pos": 3
            },
            {
              "hn": 12,
              "pop": 2,
              "odds": 2.3,
              "pos": 1
            }
          ]
        },
        {
          "raceNo": 5,
          "entries": [
            {
              "hn": 1,
              "pop": 7,
              "odds": 13.7,
              "pos": 2
            },
            {
              "hn": 2,
              "pop": 9,
              "odds": 20.5,
              "pos": null
            },
            {
              "hn": 3,
              "pop": 11,
              "odds": 373.7,
              "pos": null
            },
            {
              "hn": 4,
              "pop": 3,
              "odds": 6.0,
              "pos": null
            },
            {
              "hn": 5,
              "pop": 6,
              "odds": 12.8,
              "pos": null
            },
            {
              "hn": 6,
              "pop": 10,
              "odds": 33.3,
              "pos": null
            },
            {
              "hn": 7,
              "pop": 8,
              "odds": 16.7,
              "pos": null
            },
            {
              "hn": 8,
              "pop": 5,
              "odds": 12.4,
              "pos": 3
            },
            {
              "hn": 9,
              "pop": 1,
              "odds": 3.1,
              "pos": null
            },
            {
              "hn": 10,
              "pop": 2,
              "odds": 3.3,
              "pos": 1
            },
            {
              "hn": 11,
              "pop": 4,
              "odds": 10.0,
              "pos": null
            },
            {
              "hn": 12,
              "pop": null,
              "odds": null,
              "pos": null
            }
          ]
        },
        {
          "raceNo": 6,
          "entries": [
            {
              "hn": 1,
              "pop": 4,
              "odds": 11.4,
              "pos": null
            },
            {
              "hn": 2,
              "pop": 9,
              "odds": 19.9,
              "pos": 2
            },
            {
              "hn": 3,
              "pop": 6,
              "odds": 14.0,
              "pos": null
            },
            {
              "hn": 4,
              "pop": 2,
              "odds": 3.0,
              "pos": null
            },
            {
              "hn": 5,
              "pop": 12,
              "odds": 323.4,
              "pos": null
            },
            {
              "hn": 6,
              "pop": 11,
              "odds": 85.8,
              "pos": null
            },
            {
              "hn": 7,
              "pop": 3,
              "odds": 9.6,
              "pos": 3
            },
            {
              "hn": 8,
              "pop": 8,
              "odds": 17.9,
              "pos": null
            },
            {
              "hn": 9,
              "pop": 7,
              "odds": 15.4,
              "pos": null
            },
            {
              "hn": 10,
              "pop": 5,
              "odds": 13.9,
              "pos": null
            },
            {
              "hn": 11,
              "pop": 10,
              "odds": 53.2,
              "pos": null
            },
            {
              "hn": 12,
              "pop": 1,
              "odds": 2.6,
              "pos": 1
            }
          ]
        },
        {
          "raceNo": 7,
          "entries": [
            {
              "hn": 1,
              "pop": 8,
              "odds": 48.7,
              "pos": null
            },
            {
              "hn": 2,
              "pop": 5,
              "odds": 14.8,
              "pos": 3
            },
            {
              "hn": 3,
              "pop": 6,
              "odds": 15.1,
              "pos": null
            },
            {
              "hn": 4,
              "pop": 2,
              "odds": 2.6,
              "pos": 1
            },
            {
              "hn": 5,
              "pop": 7,
              "odds": 35.4,
              "pos": null
            },
            {
              "hn": 6,
              "pop": 11,
              "odds": 108.4,
              "pos": null
            },
            {
              "hn": 7,
              "pop": 12,
              "odds": 166.3,
              "pos": null
            },
            {
              "hn": 8,
              "pop": 10,
              "odds": 70.1,
              "pos": null
            },
            {
              "hn": 9,
              "pop": 3,
              "odds": 7.1,
              "pos": null
            },
            {
              "hn": 10,
              "pop": 1,
              "odds": 2.3,
              "pos": 2
            },
            {
              "hn": 11,
              "pop": 4,
              "odds": 11.1,
              "pos": null
            },
            {
              "hn": 12,
              "pop": 9,
              "odds": 64.8,
              "pos": null
            }
          ]
        },
        {
          "raceNo": 8,
          "entries": [
            {
              "hn": 1,
              "pop": 5,
              "odds": 6.7,
              "pos": 2
            },
            {
              "hn": 2,
              "pop": null,
              "odds": null,
              "pos": null
            },
            {
              "hn": 3,
              "pop": 4,
              "odds": 5.0,
              "pos": 1
            },
            {
              "hn": 4,
              "pop": 3,
              "odds": 4.4,
              "pos": null
            },
            {
              "hn": 5,
              "pop": 11,
              "odds": 245.1,
              "pos": 3
            },
            {
              "hn": 6,
              "pop": 7,
              "odds": 25.5,
              "pos": null
            },
            {
              "hn": 7,
              "pop": 8,
              "odds": 58.1,
              "pos": null
            },
            {
              "hn": 8,
              "pop": 9,
              "odds": 118.4,
              "pos": null
            },
            {
              "hn": 9,
              "pop": 10,
              "odds": 238.2,
              "pos": null
            },
            {
              "hn": 10,
              "pop": 2,
              "odds": 3.8,
              "pos": null
            },
            {
              "hn": 11,
              "pop": 6,
              "odds": 17.7,
              "pos": null
            },
            {
              "hn": 12,
              "pop": 1,
              "odds": 3.4,
              "pos": null
            }
          ]
        },
        {
          "raceNo": 9,
          "entries": [
            {
              "hn": 1,
              "pop": 11,
              "odds": 136.7,
              "pos": null
            },
            {
              "hn": 2,
              "pop": 7,
              "odds": 63.7,
              "pos": null
            },
            {
              "hn": 3,
              "pop": 1,
              "odds": 1.1,
              "pos": 1
            },
            {
              "hn": 4,
              "pop": 5,
              "odds": 16.2,
              "pos": null
            },
            {
              "hn": 5,
              "pop": 9,
              "odds": 86.6,
              "pos": 3
            },
            {
              "hn": 6,
              "pop": 8,
              "odds": 66.0,
              "pos": null
            },
            {
              "hn": 7,
              "pop": 2,
              "odds": 9.2,
              "pos": null
            },
            {
              "hn": 8,
              "pop": 4,
              "odds": 14.3,
              "pos": null
            },
            {
              "hn": 9,
              "pop": 12,
              "odds": 140.5,
              "pos": null
            },
            {
              "hn": 10,
              "pop": 10,
              "odds": 101.1,
              "pos": null
            },
            {
              "hn": 11,
              "pop": 6,
              "odds": 40.3,
              "pos": 2
            },
            {
              "hn": 12,
              "pop": 3,
              "odds": 13.4,
              "pos": null
            }
          ]
        },
        {
          "raceNo": 10,
          "entries": [
            {
              "hn": 1,
              "pop": 11,
              "odds": 200.7,
              "pos": null
            },
            {
              "hn": 2,
              "pop": 8,
              "odds": 65.2,
              "pos": null
            },
            {
              "hn": 3,
              "pop": 10,
              "odds": 117.2,
              "pos": null
            },
            {
              "hn": 4,
              "pop": 9,
              "odds": 102.2,
              "pos": null
            },
            {
              "hn": 5,
              "pop": 7,
              "odds": 55.6,
              "pos": null
            },
            {
              "hn": 6,
              "pop": 4,
              "odds": 8.3,
              "pos": null
            },
            {
              "hn": 7,
              "pop": 1,
              "odds": 1.6,
              "pos": 1
            },
            {
              "hn": 8,
              "pop": 6,
              "odds": 19.9,
              "pos": null
            },
            {
              "hn": 9,
              "pop": null,
              "odds": null,
              "pos": null
            },
            {
              "hn": 10,
              "pop": 5,
              "odds": 10.8,
              "pos": 3
            },
            {
              "hn": 11,
              "pop": 2,
              "odds": 5.4,
              "pos": null
            },
            {
              "hn": 12,
              "pop": 3,
              "odds": 7.3,
              "pos": 2
            }
          ]
        },
        {
          "raceNo": 11,
          "entries": [
            {
              "hn": 1,
              "pop": 11,
              "odds": 127.3,
              "pos": null
            },
            {
              "hn": 2,
              "pop": 5,
              "odds": 19.2,
              "pos": null
            },
            {
              "hn": 3,
              "pop": 9,
              "odds": 101.6,
              "pos": null
            },
            {
              "hn": 4,
              "pop": 3,
              "odds": 9.9,
              "pos": null
            },
            {
              "hn": 5,
              "pop": 1,
              "odds": 1.9,
              "pos": 1
            },
            {
              "hn": 6,
              "pop": 7,
              "odds": 51.7,
              "pos": null
            },
            {
              "hn": 7,
              "pop": 10,
              "odds": 126.2,
              "pos": null
            },
            {
              "hn": 8,
              "pop": 2,
              "odds": 2.5,
              "pos": null
            },
            {
              "hn": 9,
              "pop": 8,
              "odds": 93.0,
              "pos": 3
            },
            {
              "hn": 10,
              "pop": 4,
              "odds": 11.2,
              "pos": 2
            },
            {
              "hn": 11,
              "pop": 6,
              "odds": 23.5,
              "pos": null
            }
          ]
        },
        {
          "raceNo": 12,
          "entries": [
            {
              "hn": 1,
              "pop": 3,
              "odds": 7.6,
              "pos": 3
            },
            {
              "hn": 2,
              "pop": 5,
              "odds": 9.9,
              "pos": 2
            },
            {
              "hn": 3,
              "pop": 1,
              "odds": 2.4,
              "pos": null
            },
            {
              "hn": 4,
              "pop": 9,
              "odds": 70.3,
              "pos": null
            },
            {
              "hn": 5,
              "pop": 12,
              "odds": 387.1,
              "pos": null
            },
            {
              "hn": 6,
              "pop": 6,
              "odds": 12.5,
              "pos": 1
            },
            {
              "hn": 7,
              "pop": 8,
              "odds": 48.6,
              "pos": null
            },
            {
              "hn": 8,
              "pop": 11,
              "odds": 113.9,
              "pos": null
            },
            {
              "hn": 9,
              "pop": 4,
              "odds": 9.5,
              "pos": null
            },
            {
              "hn": 10,
              "pop": 2,
              "odds": 3.3,
              "pos": null
            },
            {
              "hn": 11,
              "pop": 10,
              "odds": 92.6,
              "pos": null
            },
            {
              "hn": 12,
              "pop": 7,
              "odds": 15.0,
              "pos": null
            }
          ]
        }
      ]
    }
  ]
}